sff/__init__.py
sff/app.py
sff-1.0.0.dist-info/LICENSE
sff-1.0.0.dist-info/METADATA
sff-1.0.0.dist-info/WHEEL
sff-1.0.0.dist-info/top_level.txt
sff-1.0.0.dist-info/RECORD
