Metadata-Version: 2.2
Name: sff
Version: 1.0.0
Summary: Mo ta ngan
Home-page: https://github.com/VuKieuAnh/sff-pypi
Author: kieuanh
Author-email: vukieuanh.hnue@gmail.com
Classifier: Programming Language :: Python :: 3
Classifier: License :: OSI Approved :: MIT License
Classifier: Operating System :: OS Independent
Requires-Python: >=3.6
License-File: LICENSE
Requires-Dist: numpy>=1.21.0
Requires-Dist: pandas>=1.3.0
Requires-Dist: scikit-learn>=1.0.2
Requires-Dist: mlxtend>=0.21.0
Requires-Dist: tffs
Dynamic: author
Dynamic: author-email
Dynamic: classifier
Dynamic: description
Dynamic: description-content-type
Dynamic: home-page
Dynamic: requires-dist
Dynamic: requires-python
Dynamic: summary
